{
  "uid": "infrastructure-overview",
  "title": "Infrastructure Overview",
  "tags": ["overview", "infrastructure"],
  "timezone": "browser",
  "editable": false,
  "refresh": "30s",
  "time": {
    "from": "now-1h",
    "to": "now"
  },
  "templating": {
    "list": []
  },
  "panels": [
    {
      "id": 1,
      "title": "Service Health",
      "type": "stat",
      "gridPos": { "h": 4, "w": 24, "x": 0, "y": 0 },
      "targets": [
        {
          "expr": "up{job=~\"auth-api|assistant-api|traefik|grafana|loki|tempo|prometheus|rabbitmq\"}",
          "legendFormat": "{{job}}"
        }
      ],
      "options": {
        "reduceOptions": { "calcs": ["lastNotNull"] },
        "colorMode": "background",
        "graphMode": "none",
        "textMode": "auto"
      },
      "fieldConfig": {
        "defaults": {
          "mappings": [
            {
              "type": "value",
              "options": { "0": { "text": "DOWN", "color": "red" }, "1": { "text": "UP", "color": "green" } }
            }
          ],
          "thresholds": {
            "mode": "absolute",
            "steps": [
              { "color": "red", "value": null },
              { "color": "green", "value": 1 }
            ]
          }
        }
      },
      "datasource": { "type": "prometheus", "uid": "prometheus" }
    },
    {
      "id": 2,
      "title": "Total Request Rate",
      "type": "timeseries",
      "gridPos": { "h": 8, "w": 8, "x": 0, "y": 4 },
      "targets": [
        {
          "expr": "sum(rate(http_server_requests_seconds_count{job=~\"auth-api|assistant-api\"}[5m]))",
          "legendFormat": "Spring Boot Services"
        },
        {
          "expr": "sum(rate(traefik_entrypoint_requests_total{entrypoint=\"websecure\"}[5m]))",
          "legendFormat": "Traefik (websecure)"
        }
      ],
      "fieldConfig": {
        "defaults": {
          "unit": "reqps",
          "custom": { "drawStyle": "line", "fillOpacity": 10, "lineWidth": 2 }
        }
      },
      "datasource": { "type": "prometheus", "uid": "prometheus" }
    },
    {
      "id": 3,
      "title": "Error Rate (5xx)",
      "type": "timeseries",
      "gridPos": { "h": 8, "w": 8, "x": 8, "y": 4 },
      "targets": [
        {
          "expr": "sum by(job)(rate(http_server_requests_seconds_count{job=~\"auth-api|assistant-api\", status=~\"5..\"}[5m]))",
          "legendFormat": "{{job}}"
        },
        {
          "expr": "sum(rate(traefik_service_requests_total{code=~\"5..\"}[5m]))",
          "legendFormat": "Traefik"
        }
      ],
      "fieldConfig": {
        "defaults": {
          "unit": "reqps",
          "custom": { "drawStyle": "line", "fillOpacity": 10, "lineWidth": 2 },
          "color": { "mode": "palette-classic" },
          "thresholds": {
            "mode": "absolute",
            "steps": [
              { "color": "green", "value": null },
              { "color": "red", "value": 1 }
            ]
          }
        }
      },
      "datasource": { "type": "prometheus", "uid": "prometheus" }
    },
    {
      "id": 4,
      "title": "P95 Latency by Service",
      "type": "timeseries",
      "gridPos": { "h": 8, "w": 8, "x": 16, "y": 4 },
      "targets": [
        {
          "expr": "histogram_quantile(0.95, sum by(job, le)(rate(http_server_requests_seconds_bucket{job=~\"auth-api|assistant-api\"}[5m])))",
          "legendFormat": "{{job}}"
        }
      ],
      "fieldConfig": {
        "defaults": {
          "unit": "s",
          "custom": { "drawStyle": "line", "fillOpacity": 10, "lineWidth": 2 }
        }
      },
      "datasource": { "type": "prometheus", "uid": "prometheus" }
    },
    {
      "id": 5,
      "title": "JVM Heap Used",
      "type": "timeseries",
      "gridPos": { "h": 8, "w": 8, "x": 0, "y": 12 },
      "targets": [
        {
          "expr": "jvm_memory_used_bytes{job=~\"auth-api|assistant-api\", area=\"heap\"}",
          "legendFormat": "{{job}} - {{instance}}"
        },
        {
          "expr": "jvm_memory_max_bytes{job=~\"auth-api|assistant-api\", area=\"heap\"}",
          "legendFormat": "{{job}} max"
        }
      ],
      "fieldConfig": {
        "defaults": {
          "unit": "bytes",
          "custom": { "drawStyle": "line", "fillOpacity": 10, "lineWidth": 2 }
        }
      },
      "datasource": { "type": "prometheus", "uid": "prometheus" }
    },
    {
      "id": 6,
      "title": "Process CPU Usage",
      "type": "timeseries",
      "gridPos": { "h": 8, "w": 8, "x": 8, "y": 12 },
      "targets": [
        {
          "expr": "process_cpu_usage{job=~\"auth-api|assistant-api\"}",
          "legendFormat": "{{job}} - {{instance}}"
        },
        {
          "expr": "system_cpu_usage{job=~\"auth-api|assistant-api\"}",
          "legendFormat": "{{job}} system"
        }
      ],
      "fieldConfig": {
        "defaults": {
          "unit": "percentunit",
          "custom": { "drawStyle": "line", "fillOpacity": 10, "lineWidth": 2 },
          "min": 0,
          "max": 1
        }
      },
      "datasource": { "type": "prometheus", "uid": "prometheus" }
    },
    {
      "id": 7,
      "title": "Error Log Rate by Container",
      "type": "timeseries",
      "gridPos": { "h": 8, "w": 8, "x": 16, "y": 12 },
      "targets": [
        {
          "datasource": { "type": "loki", "uid": "loki" },
          "expr": "sum by(container)(count_over_time({container=~\".+\"} | json | level=\"ERROR\" [5m]))",
          "legendFormat": "{{container}}"
        }
      ],
      "fieldConfig": {
        "defaults": {
          "unit": "short",
          "custom": { "drawStyle": "bars", "fillOpacity": 50, "lineWidth": 1, "stacking": { "mode": "normal" } }
        }
      }
    },
    {
      "id": 8,
      "title": "Recent Errors",
      "type": "logs",
      "gridPos": { "h": 10, "w": 24, "x": 0, "y": 20 },
      "targets": [
        {
          "datasource": { "type": "loki", "uid": "loki" },
          "expr": "{container=~\".+\"} | json | level=\"ERROR\"",
          "maxLines": 50
        }
      ],
      "options": {
        "showTime": true,
        "showLabels": true,
        "showCommonLabels": false,
        "wrapLogMessage": true,
        "prettifyLogMessage": false,
        "enableLogDetails": true,
        "sortOrder": "Descending"
      }
    }
  ],
  "schemaVersion": 39
}
